pyerrormetrics/__init__.py
pyerrormetrics/error_metrics.py
pyerrormetrics/error_quotient.py
pyerrormetrics/repeated_error_density.py
pyerrormetrics/watwin.py
pyerrormetrics-0.0.1.dist-info/LICENSE
pyerrormetrics-0.0.1.dist-info/METADATA
pyerrormetrics-0.0.1.dist-info/WHEEL
pyerrormetrics-0.0.1.dist-info/top_level.txt
pyerrormetrics-0.0.1.dist-info/RECORD
