Metadata-Version: 2.1
Name: pyerrormetrics
Version: 0.0.1
Summary: pyerrormetrics is a library designed to calculate different error metrics (Error Quotient, Repeated Error Density, Watwin Algorithm, RR Algorithm) for a given set of code executions.
Home-page: https://git.rwth-aachen.de/learntech-lufgi9/public/pyerrormetrics
Author: Annabell Brocker,The Learning Technologies Research Group,RWTH Aachen University
Author-email: a.brocker@cs.rwth-aachen.de
License: MIT
Platform: any
Classifier: Programming Language :: Python :: 3
Classifier: License :: OSI Approved :: MIT License
Classifier: Operating System :: OS Independent
Requires-Python: >=3.9
License-File: LICENSE
Requires-Dist: Levenshtein
Requires-Dist: datetime
Requires-Dist: statistics
Requires-Dist: pandas
